beautiplot/__init__.py
beautiplot/_config.py
beautiplot/plot.py
beautiplot/py.typed
beautiplot-1.1.0.dist-info/METADATA
beautiplot-1.1.0.dist-info/WHEEL
beautiplot-1.1.0.dist-info/licenses/LICENSE
beautiplot-1.1.0.dist-info/RECORD
