Metadata-Version: 2.4
Name: beautiplot
Version: 1.1.0
Summary: This package provides a set of functions to create beautiful plots with Matplotlib.
Project-URL: Homepage, https://patrick-egenlauf.github.io/beautiplot/
Project-URL: Repository, https://github.com/patrick-egenlauf/beautiplot
Project-URL: Documentation, https://patrick-egenlauf.github.io/beautiplot/
Author-email: Patrick Egenlauf <patrick.egenlauf@simtech.uni-stuttgart.de>
License-File: LICENSE
Classifier: Intended Audience :: Developers
Classifier: Programming Language :: Python
Classifier: Programming Language :: Python :: 3
Classifier: Programming Language :: Python :: 3.11
Classifier: Programming Language :: Python :: 3.12
Classifier: Programming Language :: Python :: 3.13
Classifier: Topic :: Software Development :: Libraries :: Python Modules
Requires-Python: <4.0,>=3.11
Requires-Dist: matplotlib>=3.10.5
Requires-Dist: numpy>=2.1.2
